survtur_glacier/__init__.py
survtur_glacier/common/__init__.py
survtur_glacier/common/config.py
survtur_glacier/common/default_config.ini
survtur_glacier/common/fast_glacier.py
survtur_glacier/common/helpers.py
survtur_glacier/common/human_readable.py
survtur_glacier/common/iopart2.py
survtur_glacier/common/json_things.py
survtur_glacier/common/stream_line_reader.py
survtur_glacier/common/stream_retreiver.py
survtur_glacier/glacier/__init__.py
survtur_glacier/glacier/enums.py
survtur_glacier/glacier/errors.py
survtur_glacier/glacier/hasher.py
survtur_glacier/glacier/inventory.py
survtur_glacier/glacier/survtur_glacier.py
survtur_glacier/glacier/stubs/__init__.py
survtur_glacier/glacier/stubs/archive.py
survtur_glacier/glacier/stubs/vaultdict.py
survtur_glacier/mp/__init__.py
survtur_glacier/mp/general_manager.py
survtur_glacier/mp/one_task.py
survtur_glacier/mp/progress_processor.py
survtur_glacier/mp/sqlite_tasks_queue.py
survtur_glacier/mp/stubs.py
survtur_glacier/mp/task_adder.py
survtur_glacier/mp/tasks_processor.py
survtur_glacier/mp/uploads_db.py
survtur_glacier/mp/tasks/__init__.py
survtur_glacier/mp/tasks/abstract.py
survtur_glacier/mp/tasks/downloads.py
survtur_glacier/mp/tasks/dummy.py
survtur_glacier/mp/tasks/errors.py
survtur_glacier/mp/tasks/id_gen.py
survtur_glacier/mp/tasks/initiate_upload.py
survtur_glacier/mp/tasks/inventory.py
survtur_glacier/mp/tasks/upload_part.py
survtur_glacier/qts/__init__.py
survtur_glacier/qts/items_emitter_thread.py
survtur_glacier/qts/mainwindow.py
survtur_glacier/qts/start_gui.py
survtur_glacier/qts/tier_dialog.py
survtur_glacier/qts/tierdialog_qt5.py
survtur_glacier/qts/widgets/__init__.py
survtur_glacier/qts/widgets/custom_sortable.py
survtur_glacier/qts/widgets/inventory_model.py
survtur_glacier/qts/widgets/inventory_model_base.py
survtur_glacier/qts/widgets/inventory_table_view.py
survtur_glacier/qts/widgets/sample.py
survtur_glacier/qts/widgets/tasks_table.py
survtur_glacier-2022.4a12.dist-info/LICENSE.txt
survtur_glacier-2022.4a12.dist-info/METADATA
survtur_glacier-2022.4a12.dist-info/WHEEL
survtur_glacier-2022.4a12.dist-info/entry_points.txt
survtur_glacier-2022.4a12.dist-info/top_level.txt
survtur_glacier-2022.4a12.dist-info/RECORD
