Metadata-Version: 2.1
Name: survtur-glacier
Version: 2022.4a12
Summary: GUI to work with AWS Glacier cold storage
Home-page: https://github.com/survtur/survtur-glacier
Author: Alexander Chzhen
Author-email: survtur@ya.ru
License: UNKNOWN
Platform: UNKNOWN
Classifier: Programming Language :: Python :: 3.8
Classifier: License :: OSI Approved :: GNU General Public License v3 (GPLv3)
Classifier: Operating System :: OS Independent
Requires-Python: >=3.8
License-File: LICENSE.txt
Requires-Dist: boto3
Requires-Dist: PyQt5
